darktrace-1.1.2.dist-info/licenses/LICENSE
darktrace_locks/__init__.py
darktrace_locks/ai_assistant.py
darktrace_locks/assistant_ui.py
darktrace_locks/core.py
darktrace_locks/email_handler.py
darktrace_locks/reverse_image.py
darktrace_locks/scraper.py
darktrace_locks/security.py
darktrace_locks/setup_mode.py
darktrace_locks/utils.py
darktrace_locks/assets/anuj_face.png
darktrace_locks/assets/logo.png.png
darktrace-1.1.2.dist-info/METADATA
darktrace-1.1.2.dist-info/WHEEL
darktrace-1.1.2.dist-info/entry_points.txt
darktrace-1.1.2.dist-info/top_level.txt
darktrace-1.1.2.dist-info/RECORD
