Metadata-Version: 2.4
Name: darktrace
Version: 1.1.2
Summary: DARKTRACE: Advanced Secure Lock & Reverse Search System with AI Assistant
Home-page: https://github.com/CURE0FFICIAL/darktrace-locks
Author: CURE
Classifier: Programming Language :: Python :: 3
Classifier: License :: OSI Approved :: MIT License
Classifier: Operating System :: OS Independent
Requires-Python: >=3.8
License-File: LICENSE
Requires-Dist: cryptography
Requires-Dist: requests
Requires-Dist: Pillow
Requires-Dist: pyttsx3
Requires-Dist: openai
Requires-Dist: keyboard
Requires-Dist: beautifulsoup4
Requires-Dist: simpleaudio
Requires-Dist: pyaudio
Requires-Dist: getpass4
Requires-Dist: langdetect
Requires-Dist: googletrans==4.0.0rc1
Requires-Dist: lxml
Dynamic: author
Dynamic: classifier
Dynamic: description
Dynamic: description-content-type
Dynamic: home-page
Dynamic: license-file
Dynamic: requires-dist
Dynamic: requires-python
Dynamic: summary
